{
  "artifact_count": 11,
  "artifacts": [
    {
      "asset_id": "aide-lite-pack-v0.checksums.json",
      "included": true,
      "kind": "checksums",
      "path": ".aide/release/dist/aide-lite-pack-v0.checksums.json",
      "publish_candidate": false,
      "reason": "generated local release artifact",
      "sha256": "8498cee9dd0ae28eb5d37b22bf8c2fd79963a14274893e55991696d16b177824",
      "size_bytes": 1200,
      "source": "release_dist",
      "validation_status": "pending"
    },
    {
      "asset_id": "aide-lite-pack-v0.tar.gz",
      "included": true,
      "kind": "tar_gz_archive",
      "path": ".aide/release/dist/aide-lite-pack-v0.tar.gz",
      "publish_candidate": false,
      "reason": "generated local release artifact",
      "sha256": "a92d468eaedba29abb79557851ed3fe5226c6bcfda2a522ed9fb13d2548e93d7",
      "size_bytes": 493045,
      "source": "release_dist",
      "validation_status": "pending"
    },
    {
      "asset_id": "aide-lite-pack-v0.zip",
      "included": true,
      "kind": "zip_archive",
      "path": ".aide/release/dist/aide-lite-pack-v0.zip",
      "publish_candidate": false,
      "reason": "generated local release artifact",
      "sha256": "8fb17229ac54d9355170a28b6e4bce3182cf6ad1078d4e30c81f7d5ea461d660",
      "size_bytes": 747422,
      "source": "release_dist",
      "validation_status": "pending"
    },
    {
      "asset_id": "CHANGELOG.preview.md",
      "included": true,
      "kind": "changelog_preview_copy",
      "path": ".aide/release/dist/CHANGELOG.preview.md",
      "publish_candidate": false,
      "reason": "generated local release artifact",
      "sha256": "5469c48909af069e164918de9cddd0bc0f702411e59bfb6ad8eeab3526823e3e",
      "size_bytes": 556,
      "source": "release_dist",
      "validation_status": "pending"
    },
    {
      "asset_id": "install.md",
      "included": true,
      "kind": "install_notes",
      "path": ".aide/release/dist/install.md",
      "publish_candidate": false,
      "reason": "generated local release artifact",
      "sha256": "0c3798a4e10ed6f083f4d1b9fcd7c75ea0e54a66bef3e995a2ea0e564fbe244d",
      "size_bytes": 1251,
      "source": "release_dist",
      "validation_status": "pending"
    },
    {
      "asset_id": "manifest.yaml",
      "included": true,
      "kind": "manifest",
      "path": ".aide/release/dist/manifest.yaml",
      "publish_candidate": false,
      "reason": "generated local release artifact",
      "sha256": "0cc9793f69c9099f11bceb8f3d144d5cddc0d61bb25d99036420ecb0a4803065",
      "size_bytes": 1403,
      "source": "release_dist",
      "validation_status": "pending"
    },
    {
      "asset_id": "release-provenance.json",
      "included": true,
      "kind": "provenance_report",
      "path": ".aide/release/dist/release-provenance.json",
      "publish_candidate": false,
      "reason": "generated local release artifact",
      "sha256": "70afe5f78256cde212642a9117be1d98ee9d5d998d6fc4b478387312d7a956b0",
      "size_bytes": 1440,
      "source": "release_dist",
      "validation_status": "pending"
    },
    {
      "asset_id": "release-validation.json",
      "included": true,
      "kind": "validation_report",
      "path": ".aide/release/dist/release-validation.json",
      "publish_candidate": false,
      "reason": "generated local release artifact",
      "sha256": "746317110fd2e5cc0a6fcd41715839045d11232ce0b5e011a6658d56166528af",
      "size_bytes": 3418,
      "source": "release_dist",
      "validation_status": "pending"
    },
    {
      "asset_id": "release-validation.md",
      "included": true,
      "kind": "validation_report",
      "path": ".aide/release/dist/release-validation.md",
      "publish_candidate": false,
      "reason": "generated local release artifact",
      "sha256": "df35747cfd0d9361cf1dfd5d36a185bceb5e4939f0f892bb7dbb97da16040aae",
      "size_bytes": 239,
      "source": "release_dist",
      "validation_status": "pending"
    },
    {
      "asset_id": "RELEASE_NOTES.preview.md",
      "included": true,
      "kind": "release_notes_preview_copy",
      "path": ".aide/release/dist/RELEASE_NOTES.preview.md",
      "publish_candidate": false,
      "reason": "generated local release artifact",
      "sha256": "52dd1ed2bb305a45a59ec5ca2cb55eba8c8316b17d1c8b89c127789d8fd89b02",
      "size_bytes": 752,
      "source": "release_dist",
      "validation_status": "pending"
    },
    {
      "asset_id": "SHA256SUMS.txt",
      "included": true,
      "kind": "sha256sums_text",
      "path": ".aide/release/dist/SHA256SUMS.txt",
      "publish_candidate": false,
      "reason": "generated local release artifact",
      "sha256": "2c0b0537c4c03e0cc6e82653a16a076bbc9fe70540a62b51e967fa0a1edc0dcb",
      "size_bytes": 690,
      "source": "release_dist",
      "validation_status": "pending"
    }
  ],
  "bundle_id": "aide-lite-pack-v0-1dacef0b00ef02ee",
  "no_publish": true,
  "schema_version": "aide.release-assets.v0"
}
